MANIFEST.in
README.md
setup.py
version.txt
auror_core/__init__.py
auror_core/job.py
auror_core/params.py
auror_core.egg-info/PKG-INFO
auror_core.egg-info/SOURCES.txt
auror_core.egg-info/dependency_links.txt
auror_core.egg-info/requires.txt
auror_core.egg-info/top_level.txt
auror_core/v1/__init__.py
auror_core/v1/job.py
auror_core/v1/params.py
auror_core/v2/__init__.py
auror_core/v2/dumper.py
auror_core/v2/job.py
auror_core/v2/loader.py
auror_core/v2/params.py
tests/__init__.py
tests/integration/__init__.py
tests/integration/test_job_integration.py
tests/unit/__init__.py
tests/unit/v1/__init__.py
tests/unit/v1/test_job.py
tests/unit/v1/test_params.py
tests/unit/v2/__init__.py
tests/unit/v2/test_command_job.py
tests/unit/v2/test_dumper.py
tests/unit/v2/test_job.py
tests/unit/v2/test_loader.py
tests/unit/v2/test_params.py