Metadata-Version: 2.1
Name: auror-core
Version: 1.2.0
Summary: Doing Jobs Dinamically with Azkaban
Home-page: UNKNOWN
Author: Big Data
Author-email: bigdata@corp.globo.com
License: MIT
Platform: UNKNOWN
Provides-Extra: test
